MANIFEST.in
README.md
requirements.txt
setup.cfg
setup.py
betdaq/__init__.py
betdaq/apiclient.py
betdaq/baseclient.py
betdaq/compat.py
betdaq/enums.py
betdaq/exceptions.py
betdaq/filters.py
betdaq/utils.py
betdaq/classifiers/__init__.py
betdaq/classifiers/betting.py
betdaq/classifiers/marketdata.py
betdaq/endpoints/__init__.py
betdaq/endpoints/account.py
betdaq/endpoints/baseendpoint.py
betdaq/endpoints/betting.py
betdaq/endpoints/marketdata.py
betdaq/endpoints/trading.py
betdaq/errorparsers/__init__.py
betdaq/errorparsers/betting.py
betdaq/errorparsers/marketdata.py
betdaq/resources/__init__.py
betdaq/resources/accountresources.py
betdaq/resources/baseresources.py
betdaq/resources/bettingresources.py
betdaq/resources/marketdataresources.py
betdaq/resources/tradingresources.py
betdaq_cadenza.egg-info/PKG-INFO
betdaq_cadenza.egg-info/SOURCES.txt
betdaq_cadenza.egg-info/dependency_links.txt
betdaq_cadenza.egg-info/requires.txt
betdaq_cadenza.egg-info/top_level.txt
tests/__init__.py
tests/test_account.py
tests/test_apiclient.py
tests/test_baseclient.py
tests/test_betting.py
tests/test_marketdata.py
tests/test_trading.py