Metadata-Version: 1.0
Name: betdaq-cadenza
Version: 0.0.9
Summary: Betdaq API Python wrapper
Home-page: https://github.com/grosgrosbg/betdaq
Author: Benjamin Bezias
Author-email: benjaminbezias@gmail.com
License: UNKNOWN
Platform: UNKNOWN
